asynclcron/__init__.py
asynclcron/lcron.py
asynclcron-1.0.0.dist-info/LICENSE.MD
asynclcron-1.0.0.dist-info/METADATA
asynclcron-1.0.0.dist-info/WHEEL
asynclcron-1.0.0.dist-info/top_level.txt
asynclcron-1.0.0.dist-info/RECORD
