Metadata-Version: 2.1
Name: asynclcron
Version: 1.0.0
Summary: lightweight cron by asyncio
Author-email: Zhuo Wang <zhuowang10@gmail.com>
Project-URL: Homepage, https://github.com/zhuowang10/asynclcron
Classifier: Programming Language :: Python :: 3
Classifier: License :: OSI Approved :: MIT License
Classifier: Operating System :: OS Independent
Requires-Python: <4,>=3.7
License-File: LICENSE.MD
Requires-Dist: croniter >=3.0.3
